path2vec/__init__.py
path2vec/path2vec.py
path2vec-0.0.1.dist-info/LICENSE.txt
path2vec-0.0.1.dist-info/METADATA
path2vec-0.0.1.dist-info/WHEEL
path2vec-0.0.1.dist-info/top_level.txt
path2vec-0.0.1.dist-info/RECORD
